pysegmenttree/__init__.py
pysegmenttree/c_extensions.c
pysegmenttree/c_extensions.pyi
pysegmenttree/_segmenttree.py
pysegmenttree/py.typed
pysegmenttree/_pysegmenttree_py.py
pysegmenttree/c_extensions.cpython-39-i386-linux-gnu.so
pysegmenttree/test_utils.py
pysegmenttree/_abc.py
pysegmenttree/after.txt
pysegmenttree/_extensions/intsegmenttree.h
pysegmenttree/_extensions/floatsegmenttree.h
pysegmenttree/_extensions/common.h
pysegmenttree-0.2.0.dist-info/LICENSE
pysegmenttree-0.2.0.dist-info/top_level.txt
pysegmenttree-0.2.0.dist-info/RECORD
pysegmenttree-0.2.0.dist-info/WHEEL
pysegmenttree-0.2.0.dist-info/METADATA
