Metadata-Version: 2.1
Name: pysegmenttree
Version: 0.2.0
Summary: Segment Tree for python 3+
Home-page: https://github.com/greshilov/pysegmenttree.git
Author: Viacheslav Greshilov
Author-email: s@greshilov.me
License: MIT
Keywords: segment,tree,range,segment tree
Platform: UNKNOWN
Classifier: Development Status :: 4 - Beta
Classifier: Intended Audience :: Developers
Classifier: License :: OSI Approved :: MIT License
Classifier: Operating System :: POSIX
Classifier: Operating System :: MacOS :: MacOS X
Classifier: Operating System :: Microsoft :: Windows
Classifier: Programming Language :: Python
Classifier: Programming Language :: Python :: 3
Classifier: Programming Language :: Python :: 3.6
Classifier: Programming Language :: Python :: 3.7
Classifier: Programming Language :: Python :: 3.8
Classifier: Programming Language :: Python :: 3.9
Classifier: Topic :: Software Development
Classifier: Topic :: Software Development :: Libraries
Requires-Python: >=3.6
